README.md
setup.py
overdark/__init__.py
overdark/__main__.py
overdark.egg-info/PKG-INFO
overdark.egg-info/SOURCES.txt
overdark.egg-info/dependency_links.txt
overdark.egg-info/requires.txt
overdark.egg-info/top_level.txt