Metadata-Version: 2.1
Name: overdark
Version: 2.0
Summary: Python3 Library for OverDark API
Home-page: https://github.com/tappo03/overdark_python
Author: Valerio
Author-email: info@tappo03.it
License: UNKNOWN
Download-URL: https://github.com/tappo03/overdark_pythonarchive/v_01.tar.gz
Platform: UNKNOWN
Classifier: Programming Language :: Python :: 3.8
Classifier: License :: OSI Approved :: MIT License
Classifier: Operating System :: OS Independent
